dmme/__init__.py
dmme/trainer.py
dmme/callbacks/__init__.py
dmme/callbacks/ema.py
dmme/callbacks/generate.py
dmme/common/__init__.py
dmme/common/noise.py
dmme/common/norm.py
dmme/common/vis.py
dmme/data_modules/__init__.py
dmme/data_modules/cifar10.py
dmme/data_modules/data_module.py
dmme/data_modules/lsun.py
dmme/datasets/__init__.py
dmme/datasets/lsun.py
dmme/diffusion_models/__init__.py
dmme/diffusion_models/ddim.py
dmme/diffusion_models/ddpm.py
dmme/diffusion_models/iddpm.py
dmme/equations/__init__.py
dmme/equations/ddim/__init__.py
dmme/equations/ddim/ddim.py
dmme/equations/ddpm/__init__.py
dmme/equations/ddpm/ddpm.py
dmme/equations/ddpm/losses.py
dmme/equations/iddpm/__init__.py
dmme/equations/iddpm/iddpm.py
dmme/equations/iddpm/losses.py
dmme/guidance/__init__.py
dmme/guidance/classifier.py
dmme/lit_modules/__init__.py
dmme/lit_modules/ddim.py
dmme/lit_modules/ddpm.py
dmme/lit_modules/iddpm.py
dmme/lr_scheduler/__init__.py
dmme/lr_scheduler/warmup.py
dmme/models/__init__.py
dmme/models/ddpm.py
dmme/models/iddpm.py
dmme-0.5.2.dist-info/LICENSE
dmme-0.5.2.dist-info/METADATA
dmme-0.5.2.dist-info/WHEEL
dmme-0.5.2.dist-info/entry_points.txt
dmme-0.5.2.dist-info/top_level.txt
dmme-0.5.2.dist-info/RECORD
