Metadata-Version: 2.1
Name: dmme
Version: 0.5.2
Summary: Diffusion Models Made Easy
Home-page: https://github.com/urw7rs/diffusion-models-made-easy
Author: Chanhyuk Jung
Requires-Python: >=3.7
License-File: LICENSE
Requires-Dist: torch
Requires-Dist: torchvision
Requires-Dist: einops
Requires-Dist: pytorch-lightning (>=1.8)
Requires-Dist: jsonargparse[signatures] (>=4.12.0)
Requires-Dist: torchmetrics[image]
Requires-Dist: wandb
Requires-Dist: lmdb
Requires-Dist: pillow (==9.4)
Provides-Extra: dev
Requires-Dist: black ; extra == 'dev'
Requires-Dist: flake8 ; extra == 'dev'
Requires-Dist: sphinx-autobuild ; extra == 'dev'
Requires-Dist: bumpver ; extra == 'dev'
Provides-Extra: docs
Requires-Dist: sphinx ; extra == 'docs'
Requires-Dist: myst-parser ; extra == 'docs'
Requires-Dist: furo ; extra == 'docs'
Requires-Dist: sphinxcontrib-katex ; extra == 'docs'
